drf_metadata/__init__.py
drf_metadata/meta.py
drf_metadata-0.1.12.dist-info/DESCRIPTION.rst
drf_metadata-0.1.12.dist-info/METADATA
drf_metadata-0.1.12.dist-info/RECORD
drf_metadata-0.1.12.dist-info/WHEEL
drf_metadata-0.1.12.dist-info/metadata.json
drf_metadata-0.1.12.dist-info/top_level.txt
pytests/__init__.py
pytests/django_settings.py
pytests/test_bugfixes.py
pytests/test_metadata.py
pytests/utils.py
pytests/test_app/__init__.py
pytests/test_app/models.py
pytests/test_app/migrations/0001_initial.py
pytests/test_app/migrations/__init__.py
