Metadata-Version: 2.0
Name: drf-metadata
Version: 0.1.12
Summary: Metadata generator for Django Rest Framework
Home-page: https://github.com/night-crawler/drf-metadata
Author: night-crawler
Author-email: lilo.panic@gmail.com
License: MIT
Platform: UNKNOWN
Classifier: Environment :: Web Environment
Classifier: Intended Audience :: Developers
Classifier: Operating System :: OS Independent
Classifier: Programming Language :: Python
Classifier: Programming Language :: Python :: 3
Classifier: Programming Language :: Python :: 3.5
Classifier: License :: OSI Approved :: MIT License
Requires: django
Requires: djangorestframework
